README
setup.py
Flask_XML_RPC.egg-info/PKG-INFO
Flask_XML_RPC.egg-info/SOURCES.txt
Flask_XML_RPC.egg-info/dependency_links.txt
Flask_XML_RPC.egg-info/namespace_packages.txt
Flask_XML_RPC.egg-info/not-zip-safe
Flask_XML_RPC.egg-info/requires.txt
Flask_XML_RPC.egg-info/top_level.txt
flaskext/__init__.py
flaskext/xmlrpc.py